ztplite/__init__.py
ztplite/ztplargs.py
ztplite/ztplconfiguration.py
ztplite/ztplcontroller.py
ztplite/ztplfmg.py
ztplite/ztpllogging.py
ztplite-0.2.1.dist-info/LICENSE
ztplite-0.2.1.dist-info/METADATA
ztplite-0.2.1.dist-info/WHEEL
ztplite-0.2.1.dist-info/top_level.txt
ztplite-0.2.1.dist-info/RECORD
