Metadata-Version: 2.1
Name: ztplite
Version: 0.2.1
Summary: Represents the base components of the Zero Touch Provisioning Lite Process
Home-page: https://github.com/p4r4n0y1ng
Author: p4r4n0y1ng
Author-email: jhuber@fortinet.com
License: Apache 2.0
Platform: UNKNOWN
Requires-Dist: requests
Requires-Dist: Jinja2
Requires-Dist: PyYAML
Requires-Dist: pyfmg
